pydetex/__init__.py
pydetex/_fonts.py
pydetex/_gui_settings.py
pydetex/_gui_utils.py
pydetex/_symbols.py
pydetex/_utils_lang.py
pydetex/_utils_tex.py
pydetex/gui.py
pydetex/parsers.py
pydetex/pipelines.py
pydetex/utils.py
pydetex/version.py
pydetex/res/cog.ico
pydetex/res/dictionary.ico
pydetex/res/icon.gif
pydetex/res/icon.ico
pydetex/res/placeholder_en.tex
pydetex/res/placeholder_es.tex
pydetex/res/stopwords.json
pydetex/res/u_subscripts.txt
pydetex/res/u_superscripts.txt
pydetex/res/u_symbols.txt
pydetex/res/u_textbb.txt
pydetex/res/u_textbf.txt
pydetex/res/u_textcal.txt
pydetex/res/u_textfrak.txt
pydetex/res/u_textit.txt
pydetex/res/u_textmono.txt
specs/__init__.py
pydetex-1.1.1.dist-info/LICENSE
pydetex-1.1.1.dist-info/METADATA
pydetex-1.1.1.dist-info/WHEEL
pydetex-1.1.1.dist-info/entry_points.txt
pydetex-1.1.1.dist-info/top_level.txt
pydetex-1.1.1.dist-info/RECORD
