Metadata-Version: 2.2
Name: pydetex
Version: 1.1.1
Summary: An application that transforms LaTeX code to plain text
Home-page: https://pydetex.readthedocs.io
Author: Pablo Pizarro R.
Author-email: pablo@ppizarror.com
License: MIT
Project-URL: Bug Tracker, https://github.com/ppizarror/PyDetex/issues
Project-URL: Documentation, https://pydetex.readthedocs.io
Project-URL: Source Code, https://github.com/ppizarror/PyDetex
Keywords: latex detex parser gui
Platform: any
Classifier: License :: OSI Approved :: MIT License
Classifier: Natural Language :: English
Classifier: Operating System :: OS Independent
Classifier: Programming Language :: Python :: 3.7
Classifier: Programming Language :: Python :: 3.8
Classifier: Programming Language :: Python :: 3.9
Classifier: Programming Language :: Python :: 3.10
Classifier: Programming Language :: Python :: 3.11
Classifier: Programming Language :: Python :: 3.12
Classifier: Programming Language :: Python
Classifier: Topic :: Multimedia
Classifier: Topic :: Text Processing
Requires-Python: >=3.7, <4
License-File: LICENSE
Requires-Dist: beautifulsoup4>=4.11.1
Requires-Dist: flatlatex>=0.15
Requires-Dist: langdetect>=1.0.9
Requires-Dist: nltk>=3.9.1
Requires-Dist: outdated>=0.2.2
Requires-Dist: Pillow>=9.4.0
Requires-Dist: PyMultiDictionary>=1.3.2
Requires-Dist: pyperclip>=1.9.0
Requires-Dist: requests>=2.32.3
Requires-Dist: tkmacosx>=1.0.5
Provides-Extra: docs
Requires-Dist: sphinx<7; extra == "docs"
Requires-Dist: sphinx-autodoc-typehints>=1.2.0; extra == "docs"
Requires-Dist: sphinx-rtd-theme; extra == "docs"
Provides-Extra: installer
Requires-Dist: pyinstaller==6.7.0; extra == "installer"
Provides-Extra: test
Requires-Dist: nose2[coverage_plugin]; extra == "test"
Requires-Dist: pytest; extra == "test"
Dynamic: author
Dynamic: author-email
Dynamic: classifier
Dynamic: description
Dynamic: home-page
Dynamic: keywords
Dynamic: license
Dynamic: platform
Dynamic: project-url
Dynamic: provides-extra
Dynamic: requires-dist
Dynamic: requires-python
Dynamic: summary
